[{"id":"4326632543","title":"A Book","imageUrl":"https://www.publicdomainpictures.net/pictures/10000/velka/1-1210009435EGmE.jpg","description":"This is an awesome book!","price":"19"},{"title":"fff","imageUrl":"","description":"","price":"","id":"0.11592332065914857"},{"title":"ffff","imageUrl":"","description":"","price":"","id":"0.09320868450390818"},{"id":"0.05870583898986559","title":"A Book","imageUrl":"https://www.publicdomainpictures.net/pictures/10000/velka/1-1210009435EGmE.jpg","description":"This is an awesome bookddd!","price":"20.99"}]